MANIFEST.in
README.rst
setup.py
configlib/__init__.py
configlib/config_example.py
configlib/conftypes.py
configlib/core.py
configlib/prompting.py
configlib/assets/config.json
pyconfiglib.egg-info/PKG-INFO
pyconfiglib.egg-info/SOURCES.txt
pyconfiglib.egg-info/dependency_links.txt
pyconfiglib.egg-info/requires.txt
pyconfiglib.egg-info/top_level.txt
test/test_are_missing.py