Metadata-Version: 1.0
Name: pyconfiglib
Version: 1.3.3
Summary: Configuration for python made easy
Home-page: https://github.com/ddorn/pyconfiglib
Author: Diego Dorn
Author-email: diego.dorn@free.fr
License: MIT
Platform: UNKNOWN
